{"Level":295,"MaxRow":72,"MaxCol":64,"Ids":{"1":2,"2":2,"3":2,"4":2,"5":2,"6":2,"7":2,"8":2,"9":2,"10":2,"11":1,"12":1,"13":1,"14":1,"15":1,"16":1,"17":1,"18":1,"19":1,"20":1,"21":1,"22":1,"23":1,"24":1,"25":1,"26":1,"27":1,"28":1,"29":1,"30":1,"31":1,"32":1,"33":1,"34":1,"35":1,"36":1,"37":1,"38":1,"39":1,"40":1,"41":1,"42":1,"43":1,"44":1,"45":1,"46":1,"47":1,"48":1,"49":1,"50":1},"Seeds":null,"Layers":{"1":[{"ID":0,"Layer":1,"Row":11,"Col":12,"BalloonType":29,"IsHeapTile":false,"HasBalloonType":true},{"ID":0,"Layer":1,"Row":11,"Col":20,"BalloonType":13,"IsHeapTile":false,"HasBalloonType":true},{"ID":0,"Layer":1,"Row":11,"Col":28,"BalloonType":10,"IsHeapTile":false,"HasBalloonType":true},{"ID":0,"Layer":1,"Row":11,"Col":36,"BalloonType":4,"IsHeapTile":false,"HasBalloonType":true},{"ID":0,"Layer":1,"Row":11,"Col":44,"BalloonType":46,"IsHeapTile":false,"HasBalloonType":true},{"ID":0,"Layer":1,"Row":11,"Col":52,"BalloonType":28,"IsHeapTile":false,"HasBalloonType":true},{"ID":0,"Layer":1,"Row":19,"Col":28,"BalloonType":33,"IsHeapTile":false,"HasBalloonType":true},{"ID":0,"Layer":1,"Row":19,"Col":36,"BalloonType":30,"IsHeapTile":false,"HasBalloonType":true},{"ID":0,"Layer":1,"Row":27,"Col":12,"BalloonType":22,"IsHeapTile":false,"HasBalloonType":true},{"ID":0,"Layer":1,"Row":27,"Col":20,"BalloonType":9,"IsHeapTile":false,"HasBalloonType":true},{"ID":0,"Layer":1,"Row":27,"Col":28,"BalloonType":18,"IsHeapTile":false,"HasBalloonType":true},{"ID":0,"Layer":1,"Row":27,"Col":36,"BalloonType":14,"IsHeapTile":false,"HasBalloonType":true},{"ID":0,"Layer":1,"Row":27,"Col":44,"BalloonType":11,"IsHeapTile":false,"HasBalloonType":true},{"ID":0,"Layer":1,"Row":27,"Col":52,"BalloonType":7,"IsHeapTile":false,"HasBalloonType":true},{"ID":0,"Layer":1,"Row":35,"Col":12,"BalloonType":1,"IsHeapTile":false,"HasBalloonType":true},{"ID":0,"Layer":1,"Row":35,"Col":20,"BalloonType":25,"IsHeapTile":false,"HasBalloonType":true},{"ID":0,"Layer":1,"Row":35,"Col":28,"BalloonType":10,"IsHeapTile":false,"HasBalloonType":true},{"ID":0,"Layer":1,"Row":35,"Col":36,"BalloonType":50,"IsHeapTile":false,"HasBalloonType":true},{"ID":0,"Layer":1,"Row":35,"Col":44,"BalloonType":28,"IsHeapTile":false,"HasBalloonType":true},{"ID":0,"Layer":1,"Row":35,"Col":52,"BalloonType":12,"IsHeapTile":false,"HasBalloonType":true},{"ID":0,"Layer":1,"Row":43,"Col":12,"BalloonType":38,"IsHeapTile":false,"HasBalloonType":true},{"ID":0,"Layer":1,"Row":43,"Col":28,"BalloonType":32,"IsHeapTile":false,"HasBalloonType":true},{"ID":0,"Layer":1,"Row":43,"Col":36,"BalloonType":48,"IsHeapTile":false,"HasBalloonType":true},{"ID":0,"Layer":1,"Row":43,"Col":52,"BalloonType":15,"IsHeapTile":false,"HasBalloonType":true},{"ID":0,"Layer":1,"Row":51,"Col":12,"BalloonType":4,"IsHeapTile":false,"HasBalloonType":true},{"ID":0,"Layer":1,"Row":51,"Col":28,"BalloonType":6,"IsHeapTile":false,"HasBalloonType":true},{"ID":0,"Layer":1,"Row":51,"Col":36,"BalloonType":37,"IsHeapTile":false,"HasBalloonType":true},{"ID":0,"Layer":1,"Row":51,"Col":52,"BalloonType":20,"IsHeapTile":false,"HasBalloonType":true},{"ID":0,"Layer":1,"Row":59,"Col":28,"BalloonType":9,"IsHeapTile":false,"HasBalloonType":true},{"ID":0,"Layer":1,"Row":59,"Col":36,"BalloonType":26,"IsHeapTile":false,"HasBalloonType":true}],"2":[{"ID":0,"Layer":2,"Row":11,"Col":12,"BalloonType":2,"IsHeapTile":false,"HasBalloonType":true},{"ID":0,"Layer":2,"Row":11,"Col":20,"BalloonType":48,"IsHeapTile":false,"HasBalloonType":true},{"ID":0,"Layer":2,"Row":11,"Col":28,"BalloonType":26,"IsHeapTile":false,"HasBalloonType":true},{"ID":0,"Layer":2,"Row":11,"Col":36,"BalloonType":2,"IsHeapTile":false,"HasBalloonType":true},{"ID":0,"Layer":2,"Row":11,"Col":44,"BalloonType":37,"IsHeapTile":false,"HasBalloonType":true},{"ID":0,"Layer":2,"Row":11,"Col":52,"BalloonType":21,"IsHeapTile":false,"HasBalloonType":true},{"ID":0,"Layer":2,"Row":19,"Col":28,"BalloonType":13,"IsHeapTile":false,"HasBalloonType":true},{"ID":0,"Layer":2,"Row":19,"Col":36,"BalloonType":18,"IsHeapTile":false,"HasBalloonType":true},{"ID":0,"Layer":2,"Row":27,"Col":12,"BalloonType":47,"IsHeapTile":false,"HasBalloonType":true},{"ID":0,"Layer":2,"Row":27,"Col":20,"BalloonType":9,"IsHeapTile":false,"HasBalloonType":true},{"ID":0,"Layer":2,"Row":27,"Col":28,"BalloonType":5,"IsHeapTile":false,"HasBalloonType":true},{"ID":0,"Layer":2,"Row":27,"Col":36,"BalloonType":44,"IsHeapTile":false,"HasBalloonType":true},{"ID":0,"Layer":2,"Row":27,"Col":44,"BalloonType":34,"IsHeapTile":false,"HasBalloonType":true},{"ID":0,"Layer":2,"Row":27,"Col":52,"BalloonType":7,"IsHeapTile":false,"HasBalloonType":true},{"ID":0,"Layer":2,"Row":35,"Col":12,"BalloonType":1,"IsHeapTile":false,"HasBalloonType":true},{"ID":0,"Layer":2,"Row":35,"Col":20,"BalloonType":2,"IsHeapTile":false,"HasBalloonType":true},{"ID":0,"Layer":2,"Row":35,"Col":28,"BalloonType":40,"IsHeapTile":false,"HasBalloonType":true},{"ID":0,"Layer":2,"Row":35,"Col":36,"BalloonType":8,"IsHeapTile":false,"HasBalloonType":true},{"ID":0,"Layer":2,"Row":35,"Col":44,"BalloonType":24,"IsHeapTile":false,"HasBalloonType":true},{"ID":0,"Layer":2,"Row":35,"Col":52,"BalloonType":12,"IsHeapTile":false,"HasBalloonType":true},{"ID":0,"Layer":2,"Row":43,"Col":12,"BalloonType":42,"IsHeapTile":false,"HasBalloonType":true},{"ID":0,"Layer":2,"Row":43,"Col":28,"BalloonType":33,"IsHeapTile":false,"HasBalloonType":true},{"ID":0,"Layer":2,"Row":43,"Col":36,"BalloonType":36,"IsHeapTile":false,"HasBalloonType":true},{"ID":0,"Layer":2,"Row":43,"Col":52,"BalloonType":20,"IsHeapTile":false,"HasBalloonType":true},{"ID":0,"Layer":2,"Row":51,"Col":12,"BalloonType":4,"IsHeapTile":false,"HasBalloonType":true},{"ID":0,"Layer":2,"Row":51,"Col":28,"BalloonType":47,"IsHeapTile":false,"HasBalloonType":true},{"ID":0,"Layer":2,"Row":51,"Col":36,"BalloonType":50,"IsHeapTile":false,"HasBalloonType":true},{"ID":0,"Layer":2,"Row":51,"Col":52,"BalloonType":28,"IsHeapTile":false,"HasBalloonType":true},{"ID":0,"Layer":2,"Row":59,"Col":28,"BalloonType":49,"IsHeapTile":false,"HasBalloonType":true},{"ID":0,"Layer":2,"Row":59,"Col":36,"BalloonType":19,"IsHeapTile":false,"HasBalloonType":true}],"3":[{"ID":0,"Layer":3,"Row":11,"Col":12,"BalloonType":46,"IsHeapTile":false,"HasBalloonType":true},{"ID":0,"Layer":3,"Row":11,"Col":20,"BalloonType":1,"IsHeapTile":false,"HasBalloonType":true},{"ID":0,"Layer":3,"Row":11,"Col":28,"BalloonType":3,"IsHeapTile":false,"HasBalloonType":true},{"ID":0,"Layer":3,"Row":11,"Col":36,"BalloonType":45,"IsHeapTile":false,"HasBalloonType":true},{"ID":0,"Layer":3,"Row":11,"Col":44,"BalloonType":4,"IsHeapTile":false,"HasBalloonType":true},{"ID":0,"Layer":3,"Row":11,"Col":52,"BalloonType":27,"IsHeapTile":false,"HasBalloonType":true},{"ID":0,"Layer":3,"Row":19,"Col":28,"BalloonType":18,"IsHeapTile":false,"HasBalloonType":true},{"ID":0,"Layer":3,"Row":19,"Col":36,"BalloonType":3,"IsHeapTile":false,"HasBalloonType":true},{"ID":0,"Layer":3,"Row":27,"Col":12,"BalloonType":27,"IsHeapTile":false,"HasBalloonType":true},{"ID":0,"Layer":3,"Row":27,"Col":20,"BalloonType":50,"IsHeapTile":false,"HasBalloonType":true},{"ID":0,"Layer":3,"Row":27,"Col":28,"BalloonType":39,"IsHeapTile":false,"HasBalloonType":true},{"ID":0,"Layer":3,"Row":27,"Col":36,"BalloonType":46,"IsHeapTile":false,"HasBalloonType":true},{"ID":0,"Layer":3,"Row":27,"Col":44,"BalloonType":6,"IsHeapTile":false,"HasBalloonType":true},{"ID":0,"Layer":3,"Row":27,"Col":52,"BalloonType":7,"IsHeapTile":false,"HasBalloonType":true},{"ID":0,"Layer":3,"Row":35,"Col":12,"BalloonType":36,"IsHeapTile":false,"HasBalloonType":true},{"ID":0,"Layer":3,"Row":35,"Col":20,"BalloonType":3,"IsHeapTile":false,"HasBalloonType":true},{"ID":0,"Layer":3,"Row":35,"Col":28,"BalloonType":25,"IsHeapTile":false,"HasBalloonType":true},{"ID":0,"Layer":3,"Row":35,"Col":36,"BalloonType":2,"IsHeapTile":false,"HasBalloonType":true},{"ID":0,"Layer":3,"Row":35,"Col":44,"BalloonType":39,"IsHeapTile":false,"HasBalloonType":true},{"ID":0,"Layer":3,"Row":35,"Col":52,"BalloonType":7,"IsHeapTile":false,"HasBalloonType":true},{"ID":0,"Layer":3,"Row":43,"Col":12,"BalloonType":23,"IsHeapTile":false,"HasBalloonType":true},{"ID":0,"Layer":3,"Row":43,"Col":28,"BalloonType":8,"IsHeapTile":false,"HasBalloonType":true},{"ID":0,"Layer":3,"Row":43,"Col":36,"BalloonType":41,"IsHeapTile":false,"HasBalloonType":true},{"ID":0,"Layer":3,"Row":43,"Col":52,"BalloonType":15,"IsHeapTile":false,"HasBalloonType":true},{"ID":0,"Layer":3,"Row":51,"Col":12,"BalloonType":7,"IsHeapTile":false,"HasBalloonType":true},{"ID":0,"Layer":3,"Row":51,"Col":28,"BalloonType":38,"IsHeapTile":false,"HasBalloonType":true},{"ID":0,"Layer":3,"Row":51,"Col":36,"BalloonType":25,"IsHeapTile":false,"HasBalloonType":true},{"ID":0,"Layer":3,"Row":51,"Col":52,"BalloonType":16,"IsHeapTile":false,"HasBalloonType":true},{"ID":0,"Layer":3,"Row":59,"Col":28,"BalloonType":6,"IsHeapTile":false,"HasBalloonType":true},{"ID":0,"Layer":3,"Row":59,"Col":36,"BalloonType":49,"IsHeapTile":false,"HasBalloonType":true}],"4":[{"ID":0,"Layer":4,"Row":11,"Col":12,"BalloonType":33,"IsHeapTile":false,"HasBalloonType":true},{"ID":0,"Layer":4,"Row":11,"Col":20,"BalloonType":35,"IsHeapTile":false,"HasBalloonType":true},{"ID":0,"Layer":4,"Row":11,"Col":28,"BalloonType":44,"IsHeapTile":false,"HasBalloonType":true},{"ID":0,"Layer":4,"Row":11,"Col":36,"BalloonType":5,"IsHeapTile":false,"HasBalloonType":true},{"ID":0,"Layer":4,"Row":11,"Col":44,"BalloonType":27,"IsHeapTile":false,"HasBalloonType":true},{"ID":0,"Layer":4,"Row":11,"Col":52,"BalloonType":21,"IsHeapTile":false,"HasBalloonType":true},{"ID":0,"Layer":4,"Row":19,"Col":28,"BalloonType":14,"IsHeapTile":false,"HasBalloonType":true},{"ID":0,"Layer":4,"Row":19,"Col":36,"BalloonType":1,"IsHeapTile":false,"HasBalloonType":true},{"ID":0,"Layer":4,"Row":27,"Col":12,"BalloonType":1,"IsHeapTile":false,"HasBalloonType":true},{"ID":0,"Layer":4,"Row":27,"Col":20,"BalloonType":42,"IsHeapTile":false,"HasBalloonType":true},{"ID":0,"Layer":4,"Row":27,"Col":28,"BalloonType":1,"IsHeapTile":false,"HasBalloonType":true},{"ID":0,"Layer":4,"Row":27,"Col":36,"BalloonType":29,"IsHeapTile":false,"HasBalloonType":true},{"ID":0,"Layer":4,"Row":27,"Col":44,"BalloonType":10,"IsHeapTile":false,"HasBalloonType":true},{"ID":0,"Layer":4,"Row":27,"Col":52,"BalloonType":17,"IsHeapTile":false,"HasBalloonType":true},{"ID":0,"Layer":4,"Row":35,"Col":12,"BalloonType":5,"IsHeapTile":false,"HasBalloonType":true},{"ID":0,"Layer":4,"Row":35,"Col":20,"BalloonType":32,"IsHeapTile":false,"HasBalloonType":true},{"ID":0,"Layer":4,"Row":35,"Col":28,"BalloonType":32,"IsHeapTile":false,"HasBalloonType":true},{"ID":0,"Layer":4,"Row":35,"Col":36,"BalloonType":10,"IsHeapTile":false,"HasBalloonType":true},{"ID":0,"Layer":4,"Row":35,"Col":44,"BalloonType":24,"IsHeapTile":false,"HasBalloonType":true},{"ID":0,"Layer":4,"Row":35,"Col":52,"BalloonType":17,"IsHeapTile":false,"HasBalloonType":true},{"ID":0,"Layer":4,"Row":43,"Col":12,"BalloonType":9,"IsHeapTile":false,"HasBalloonType":true},{"ID":0,"Layer":4,"Row":43,"Col":28,"BalloonType":45,"IsHeapTile":false,"HasBalloonType":true},{"ID":0,"Layer":4,"Row":43,"Col":36,"BalloonType":40,"IsHeapTile":false,"HasBalloonType":true},{"ID":0,"Layer":4,"Row":43,"Col":52,"BalloonType":17,"IsHeapTile":false,"HasBalloonType":true},{"ID":0,"Layer":4,"Row":51,"Col":12,"BalloonType":39,"IsHeapTile":false,"HasBalloonType":true},{"ID":0,"Layer":4,"Row":51,"Col":28,"BalloonType":8,"IsHeapTile":false,"HasBalloonType":true},{"ID":0,"Layer":4,"Row":51,"Col":36,"BalloonType":34,"IsHeapTile":false,"HasBalloonType":true},{"ID":0,"Layer":4,"Row":51,"Col":52,"BalloonType":16,"IsHeapTile":false,"HasBalloonType":true},{"ID":0,"Layer":4,"Row":59,"Col":28,"BalloonType":19,"IsHeapTile":false,"HasBalloonType":true},{"ID":0,"Layer":4,"Row":59,"Col":36,"BalloonType":9,"IsHeapTile":false,"HasBalloonType":true}],"5":[{"ID":0,"Layer":5,"Row":11,"Col":12,"BalloonType":24,"IsHeapTile":false,"HasBalloonType":true},{"ID":0,"Layer":5,"Row":11,"Col":20,"BalloonType":3,"IsHeapTile":false,"HasBalloonType":true},{"ID":0,"Layer":5,"Row":11,"Col":28,"BalloonType":6,"IsHeapTile":false,"HasBalloonType":true},{"ID":0,"Layer":5,"Row":11,"Col":36,"BalloonType":26,"IsHeapTile":false,"HasBalloonType":true},{"ID":0,"Layer":5,"Row":11,"Col":44,"BalloonType":7,"IsHeapTile":false,"HasBalloonType":true},{"ID":0,"Layer":5,"Row":11,"Col":52,"BalloonType":49,"IsHeapTile":false,"HasBalloonType":true},{"ID":0,"Layer":5,"Row":19,"Col":28,"BalloonType":10,"IsHeapTile":false,"HasBalloonType":true},{"ID":0,"Layer":5,"Row":19,"Col":36,"BalloonType":10,"IsHeapTile":false,"HasBalloonType":true},{"ID":0,"Layer":5,"Row":27,"Col":12,"BalloonType":22,"IsHeapTile":false,"HasBalloonType":true},{"ID":0,"Layer":5,"Row":27,"Col":20,"BalloonType":43,"IsHeapTile":false,"HasBalloonType":true},{"ID":0,"Layer":5,"Row":27,"Col":28,"BalloonType":34,"IsHeapTile":false,"HasBalloonType":true},{"ID":0,"Layer":5,"Row":27,"Col":36,"BalloonType":43,"IsHeapTile":false,"HasBalloonType":true},{"ID":0,"Layer":5,"Row":27,"Col":44,"BalloonType":41,"IsHeapTile":false,"HasBalloonType":true},{"ID":0,"Layer":5,"Row":27,"Col":52,"BalloonType":11,"IsHeapTile":false,"HasBalloonType":true},{"ID":0,"Layer":5,"Row":35,"Col":12,"BalloonType":30,"IsHeapTile":false,"HasBalloonType":true},{"ID":0,"Layer":5,"Row":35,"Col":20,"BalloonType":41,"IsHeapTile":false,"HasBalloonType":true},{"ID":0,"Layer":5,"Row":35,"Col":28,"BalloonType":30,"IsHeapTile":false,"HasBalloonType":true},{"ID":0,"Layer":5,"Row":35,"Col":36,"BalloonType":35,"IsHeapTile":false,"HasBalloonType":true},{"ID":0,"Layer":5,"Row":35,"Col":44,"BalloonType":40,"IsHeapTile":false,"HasBalloonType":true},{"ID":0,"Layer":5,"Row":35,"Col":52,"BalloonType":6,"IsHeapTile":false,"HasBalloonType":true},{"ID":0,"Layer":5,"Row":43,"Col":12,"BalloonType":5,"IsHeapTile":false,"HasBalloonType":true},{"ID":0,"Layer":5,"Row":43,"Col":28,"BalloonType":45,"IsHeapTile":false,"HasBalloonType":true},{"ID":0,"Layer":5,"Row":43,"Col":36,"BalloonType":35,"IsHeapTile":false,"HasBalloonType":true},{"ID":0,"Layer":5,"Row":43,"Col":52,"BalloonType":16,"IsHeapTile":false,"HasBalloonType":true},{"ID":0,"Layer":5,"Row":51,"Col":12,"BalloonType":4,"IsHeapTile":false,"HasBalloonType":true},{"ID":0,"Layer":5,"Row":51,"Col":28,"BalloonType":38,"IsHeapTile":false,"HasBalloonType":true},{"ID":0,"Layer":5,"Row":51,"Col":36,"BalloonType":5,"IsHeapTile":false,"HasBalloonType":true},{"ID":0,"Layer":5,"Row":51,"Col":52,"BalloonType":23,"IsHeapTile":false,"HasBalloonType":true},{"ID":0,"Layer":5,"Row":59,"Col":28,"BalloonType":43,"IsHeapTile":false,"HasBalloonType":true},{"ID":0,"Layer":5,"Row":59,"Col":36,"BalloonType":6,"IsHeapTile":false,"HasBalloonType":true}],"6":[{"ID":0,"Layer":6,"Row":11,"Col":12,"BalloonType":4,"IsHeapTile":false,"HasBalloonType":true},{"ID":0,"Layer":6,"Row":11,"Col":20,"BalloonType":2,"IsHeapTile":false,"HasBalloonType":true},{"ID":0,"Layer":6,"Row":11,"Col":28,"BalloonType":13,"IsHeapTile":false,"HasBalloonType":true},{"ID":0,"Layer":6,"Row":11,"Col":36,"BalloonType":3,"IsHeapTile":false,"HasBalloonType":true},{"ID":0,"Layer":6,"Row":11,"Col":44,"BalloonType":3,"IsHeapTile":false,"HasBalloonType":true},{"ID":0,"Layer":6,"Row":11,"Col":52,"BalloonType":21,"IsHeapTile":false,"HasBalloonType":true},{"ID":0,"Layer":6,"Row":19,"Col":28,"BalloonType":2,"IsHeapTile":false,"HasBalloonType":true},{"ID":0,"Layer":6,"Row":19,"Col":36,"BalloonType":36,"IsHeapTile":false,"HasBalloonType":true},{"ID":0,"Layer":6,"Row":27,"Col":12,"BalloonType":8,"IsHeapTile":false,"HasBalloonType":true},{"ID":0,"Layer":6,"Row":27,"Col":20,"BalloonType":8,"IsHeapTile":false,"HasBalloonType":true},{"ID":0,"Layer":6,"Row":27,"Col":28,"BalloonType":44,"IsHeapTile":false,"HasBalloonType":true},{"ID":0,"Layer":6,"Row":27,"Col":36,"BalloonType":14,"IsHeapTile":false,"HasBalloonType":true},{"ID":0,"Layer":6,"Row":27,"Col":44,"BalloonType":29,"IsHeapTile":false,"HasBalloonType":true},{"ID":0,"Layer":6,"Row":27,"Col":52,"BalloonType":12,"IsHeapTile":false,"HasBalloonType":true},{"ID":0,"Layer":6,"Row":35,"Col":12,"BalloonType":22,"IsHeapTile":false,"HasBalloonType":true},{"ID":0,"Layer":6,"Row":35,"Col":20,"BalloonType":8,"IsHeapTile":false,"HasBalloonType":true},{"ID":0,"Layer":6,"Row":35,"Col":28,"BalloonType":42,"IsHeapTile":false,"HasBalloonType":true},{"ID":0,"Layer":6,"Row":35,"Col":36,"BalloonType":37,"IsHeapTile":false,"HasBalloonType":true},{"ID":0,"Layer":6,"Row":35,"Col":44,"BalloonType":23,"IsHeapTile":false,"HasBalloonType":true},{"ID":0,"Layer":6,"Row":35,"Col":52,"BalloonType":11,"IsHeapTile":false,"HasBalloonType":true},{"ID":0,"Layer":6,"Row":43,"Col":12,"BalloonType":5,"IsHeapTile":false,"HasBalloonType":true},{"ID":0,"Layer":6,"Row":43,"Col":28,"BalloonType":31,"IsHeapTile":false,"HasBalloonType":true},{"ID":0,"Layer":6,"Row":43,"Col":36,"BalloonType":31,"IsHeapTile":false,"HasBalloonType":true},{"ID":0,"Layer":6,"Row":43,"Col":52,"BalloonType":15,"IsHeapTile":false,"HasBalloonType":true},{"ID":0,"Layer":6,"Row":51,"Col":12,"BalloonType":48,"IsHeapTile":false,"HasBalloonType":true},{"ID":0,"Layer":6,"Row":51,"Col":28,"BalloonType":31,"IsHeapTile":false,"HasBalloonType":true},{"ID":0,"Layer":6,"Row":51,"Col":36,"BalloonType":47,"IsHeapTile":false,"HasBalloonType":true},{"ID":0,"Layer":6,"Row":51,"Col":52,"BalloonType":20,"IsHeapTile":false,"HasBalloonType":true},{"ID":0,"Layer":6,"Row":59,"Col":28,"BalloonType":19,"IsHeapTile":false,"HasBalloonType":true},{"ID":0,"Layer":6,"Row":59,"Col":36,"BalloonType":9,"IsHeapTile":false,"HasBalloonType":true}]},"IsCross":false,"Mix":75,"Type":2}